hydro_raster/Raster.py
hydro_raster/Tutorial.py
hydro_raster/Tutorial_carlisle.py
hydro_raster/__init__.py
hydro_raster/channel_geometry.py
hydro_raster/convert_coords.py
hydro_raster/coords_interp.py
hydro_raster/demo_functions.py
hydro_raster/grid_show.py
hydro_raster/interp_line2surface.py
hydro_raster/remove_block.py
hydro_raster/river_bed_exmaple.py
hydro_raster/spatial_analysis.py
hydro_raster/sample/CA1_5m.tif
hydro_raster/sample/CA1_overhead_features.cpg
hydro_raster/sample/CA1_overhead_features.dbf
hydro_raster/sample/CA1_overhead_features.prj
hydro_raster/sample/CA1_overhead_features.qmd
hydro_raster/sample/CA1_overhead_features.shp
hydro_raster/sample/CA1_overhead_features.shx
hydro_raster-0.0.11.dist-info/METADATA
hydro_raster-0.0.11.dist-info/WHEEL
hydro_raster-0.0.11.dist-info/top_level.txt
hydro_raster-0.0.11.dist-info/RECORD
