Metadata-Version: 2.1
Name: hydro-raster
Version: 0.0.11
Summary: To process raster data for hydrological/hydrodynamic modelling
Home-page: https://github.com/mingxiaodong/hydro-raster
Author: Xiaodong Ming
Author-email: xiaodong.ming@outlook.com
License: LICENSE.txt
Keywords: Raster Hydrological Hydrodynamic
Platform: UNKNOWN
Classifier: Development Status :: 3 - Alpha
Classifier: Programming Language :: Python :: 3
Classifier: License :: OSI Approved :: MIT License
Classifier: Programming Language :: Python :: 3
Classifier: Operating System :: OS Independent
Requires-Python: >=3.6
Requires-Dist: rasterio
Requires-Dist: scipy
Requires-Dist: shapely
Requires-Dist: pyshp
Requires-Dist: matplotlib
Requires-Dist: numpy
Requires-Dist: pandas
Requires-Dist: imageio
Requires-Dist: geopandas
